<?xml version='1.0' encoding='utf-8'?>
<Database name="nuevo">
    <Table name="ggg">
        <Estructura>
            <Principal name="idestado">
                <Atributo1 tipo="0">1</Atributo1>
                <Atributo2 nulidad="2">2</Atributo2>
                <Atributo3 restricciones="1">1</Atributo3>
            </Principal>
            <Principal name="estado">
                <Atributo1 tipo="NVARCHAR(4)">1</Atributo1>
                <Atributo2 nulidad="2">2</Atributo2>
                <Atributo3 restricciones="0">0</Atributo3>
            </Principal>
        </Estructura>
        <Datos name="nuevo_registro">
            <DatosEspecifico>
                <idestado>3</idestado>
                <estado>Queso * None.persona + None.simon</estado>
            </DatosEspecifico>
            <DatosEspecifico>
                <idestado>1</idestado>
                <estado>Activo</estado>
            </DatosEspecifico>
            <DatosEspecifico>
                <idestado>2</idestado>
                <estado>Inactivo</estado>
            </DatosEspecifico>
            <DatosEspecifico>
                <idestado>4</idestado>
                <estado>Activo2</estado>
            </DatosEspecifico>
        </Datos>
    </Table>
</Database>